[
    {
        "exercise": "Overhead press",
        "startPercent": 0.8,
        "endPercent": 1,
        "sessions": [
            {
                "date": "14/10/2016",
                "sets": [
                    {
                        "weight": 32.5,
                        "reps": 8,
                        "split": "00:00:00:000",
                        "target": true
                    },
                    {
                        "weight": 35,
                        "reps": 8,
                        "split": "00:00:00:000",
                        "target": true
                    },
                    {
                        "weight": 35,
                        "reps": 8,
                        "split": "00:01:35:884",
                        "target": true
                    },
                    {
                        "weight": 37.5,
                        "reps": 8,
                        "split": "00:02:07:317",
                        "target": true
                    },
                    {
                        "weight": 40,
                        "reps": 8,
                        "split": "00:01:57:925",
                        "target": true
                    },
                    {
                        "weight": 40,
                        "reps": 8,
                        "split": "00:02:04:301",
                        "target": true
                    },
                    {
                        "weight": 40,
                        "reps": 8,
                        "split": "00:02:31:813",
                        "target": true
                    },
                    {
                        "weight": 40,
                        "reps": 8,
                        "split": "00:02:34:031",
                        "target": true
                    },
                    {
                        "weight": 40,
                        "reps": 8,
                        "split": "00:02:35:782",
                        "target": true
                    }
                ]
            },
            {
                "date": "22/10/2016",
                "sets": [
                    {
                        "weight": 32.5,
                        "reps": 8,
                        "split": "00:00:00:000",
                        "target": true
                    },
                    {
                        "weight": 35,
                        "reps": 8,
                        "split": "00:01:44:665",
                        "target": true
                    },
                    {
                        "weight": 35,
                        "reps": 8,
                        "split": "00:01:49:679",
                        "target": true
                    },
                    {
                        "weight": 37.5,
                        "reps": 8,
                        "split": "00:02:30:304",
                        "target": true
                    },
                    {
                        "weight": 40,
                        "reps": 6,
                        "split": "00:02:27:798",
                        "target": true
                    },
                    {
                        "weight": 37.5,
                        "reps": 8,
                        "split": "00:02:02:944",
                        "target": true
                    },
                    {
                        "weight": 37.5,
                        "reps": 8,
                        "split": "00:02:23:811",
                        "target": true
                    },
                    {
                        "weight": 32.5,
                        "reps": 8,
                        "split": "00:02:04:731",
                        "target": true
                    },
                    {
                        "weight": 30,
                        "reps": 8,
                        "split": "00:02:21:565",
                        "target": true
                    }
                ]
            },
            {
                "date": "31/10/2016",
                "sets": [
                    {
                        "weight": 32.5,
                        "reps": 8,
                        "split": "00:00:00:000",
                        "target": true
                    },
                    {
                        "weight": 32.5,
                        "reps": 8,
                        "split": "00:01:54:010",
                        "target": true
                    },
                    {
                        "weight": 32.5,
                        "reps": 8,
                        "split": "00:02:51:308",
                        "target": true
                    },
                    {
                        "weight": 32.5,
                        "reps": 8,
                        "split": "00:02:14:424",
                        "target": true
                    },
                    {
                        "weight": 32.5,
                        "reps": 8,
                        "split": "00:01:57:459",
                        "target": true
                    },
                    {
                        "weight": 32.5,
                        "reps": 8,
                        "split": "00:02:07:886",
                        "target": true
                    },
                    {
                        "weight": 32.5,
                        "reps": 8,
                        "split": "00:02:30:372",
                        "target": true
                    },
                    {
                        "weight": 32.5,
                        "reps": 8,
                        "split": "00:02:27:945",
                        "target": true
                    },
                    {
                        "weight": 32.5,
                        "reps": 8,
                        "split": "00:03:59:703",
                        "target": true
                    }
                ]
            },
            {
                "date": "08/11/2016",
                "sets": [
                    {
                        "weight": 25,
                        "reps": 8,
                        "split": "00:00:00:000",
                        "target": true
                    },
                    {
                        "weight": 30,
                        "reps": 8,
                        "split": "00:02:18:436",
                        "target": true
                    },
                    {
                        "weight": 32.5,
                        "reps": 8,
                        "split": "00:02:04:897",
                        "target": true
                    },
                    {
                        "weight": 32.5,
                        "reps": 8,
                        "split": "00:01:38:237",
                        "target": true
                    },
                    {
                        "weight": 35,
                        "reps": 8,
                        "split": "00:02:23:738",
                        "target": true
                    },
                    {
                        "weight": 35,
                        "reps": 8,
                        "split": "00:02:39:313",
                        "target": true
                    },
                    {
                        "weight": 35,
                        "reps": 8,
                        "split": "00:02:21:710",
                        "target": true
                    },
                    {
                        "weight": 32.5,
                        "reps": 8,
                        "split": "00:00:14:133",
                        "target": true
                    },
                    {
                        "weight": 32.5,
                        "reps": 8,
                        "split": "00:02:08:344",
                        "target": true
                    }
                ]
            },
            {
                "date": "15/11/2016",
                "sets": [
                    {
                        "weight": 27.5,
                        "reps": 8,
                        "split": "00:00:00:000",
                        "target": true
                    },
                    {
                        "weight": 30,
                        "reps": 8,
                        "split": "00:01:50:186",
                        "target": true
                    },
                    {
                        "weight": 32.5,
                        "reps": 8,
                        "split": "00:01:43:542",
                        "target": true
                    },
                    {
                        "weight": 32.5,
                        "reps": 8,
                        "split": "00:02:06:870",
                        "target": true
                    },
                    {
                        "weight": 35,
                        "reps": 8,
                        "split": "00:02:09:670",
                        "target": true
                    },
                    {
                        "weight": 35,
                        "reps": 8,
                        "split": "00:02:30:687",
                        "target": true
                    },
                    {
                        "weight": 35,
                        "reps": 8,
                        "split": "00:02:27:291",
                        "target": true
                    },
                    {
                        "weight": 32.5,
                        "reps": 8,
                        "split": "00:02:22:635",
                        "target": true
                    },
                    {
                        "weight": 32.5,
                        "reps": 8,
                        "split": "00:03:19:948",
                        "target": true
                    }
                ]
            }
        ],
        "sets": 9,
        "reps": 8,
        "peak": 5,
        "increase": 2.5,
        "incInterval": 3,
        "equipmentWeight": 20
    },
    {
        "exercise": "Lateral Raises",
        "sets": 3,
        "increase": 2.5,
        "peak": 1,
        "startPercent": 1,
        "endPercent": 1,
        "incInterval": 4,
        "equipmentWeight": 10,
        "sessions": [
            {
                "date": "14/10/2016",
                "sets": [
                    {
                        "weight": 20,
                        "reps": 8,
                        "split": "00:00:44:010",
                        "target": true
                    },
                    {
                        "weight": 20,
                        "reps": 8,
                        "split": "00:00:06:188",
                        "target": true
                    },
                    {
                        "weight": 20,
                        "reps": 8,
                        "split": "00:00:40:350",
                        "target": true
                    }
                ]
            },
            {
                "date": "22/10/2016",
                "sets": [
                    {
                        "weight": 20,
                        "reps": 8,
                        "split": "00:01:03:892",
                        "target": true
                    },
                    {
                        "weight": 20,
                        "reps": 8,
                        "split": "00:00:46:339",
                        "target": true
                    },
                    {
                        "weight": 20,
                        "reps": 8,
                        "split": "00:00:57:824",
                        "target": true
                    }
                ]
            },
            {
                "date": "31/10/2016",
                "sets": [
                    {
                        "weight": 20,
                        "reps": 8,
                        "split": "00:00:39:603",
                        "target": true
                    },
                    {
                        "weight": 20,
                        "reps": 8,
                        "split": "00:00:47:762",
                        "target": true
                    },
                    {
                        "weight": 20,
                        "reps": 8,
                        "split": "00:00:07:327",
                        "target": true
                    }
                ]
            },
            {
                "date": "08/11/2016",
                "sets": [
                    {
                        "weight": 20,
                        "reps": 8,
                        "split": "00:00:56:622",
                        "target": true
                    },
                    {
                        "weight": 20,
                        "reps": 8,
                        "split": "00:00:50:382",
                        "target": true
                    },
                    {
                        "weight": 20,
                        "reps": 8,
                        "split": "00:01:23:544",
                        "target": true
                    }
                ]
            },
            {
                "date": "15/11/2016",
                "sets": [
                    {
                        "weight": 20,
                        "reps": 8,
                        "split": "00:00:39:846",
                        "target": true
                    },
                    {
                        "weight": 20,
                        "reps": 8,
                        "split": "00:00:26:795",
                        "target": true
                    },
                    {
                        "weight": 20,
                        "reps": 8,
                        "split": "00:00:56:103",
                        "target": true
                    }
                ]
            }
        ],
        "reps": 8
    },
    {
        "exercise": "Front Raises",
        "sets": 3,
        "increase": 2.5,
        "peak": 3,
        "startPercent": 1,
        "endPercent": 1,
        "incInterval": 4,
        "equipmentWeight": 10,
        "sessions": [
            {
                "date": "14/10/2016",
                "sets": [
                    {
                        "weight": 20,
                        "reps": 8,
                        "split": "00:01:08:319",
                        "target": true
                    },
                    {
                        "weight": 20,
                        "reps": 8,
                        "split": "00:00:53:339",
                        "target": true
                    },
                    {
                        "weight": 20,
                        "reps": 8,
                        "split": "00:01:01:735",
                        "target": true
                    }
                ]
            },
            {
                "date": "22/10/2016",
                "sets": [
                    {
                        "weight": 20,
                        "reps": 8,
                        "split": "00:00:49:391",
                        "target": true
                    },
                    {
                        "weight": 20,
                        "reps": 8,
                        "split": "00:01:11:600",
                        "target": true
                    },
                    {
                        "weight": 20,
                        "reps": 8,
                        "split": "00:00:59:735",
                        "target": true
                    }
                ]
            },
            {
                "date": "31/10/2016",
                "sets": [
                    {
                        "weight": 20,
                        "reps": 8,
                        "split": "00:00:55:567",
                        "target": true
                    },
                    {
                        "weight": 20,
                        "reps": 8,
                        "split": "00:00:42:755",
                        "target": true
                    },
                    {
                        "weight": 20,
                        "reps": 8,
                        "split": "00:00:53:577",
                        "target": true
                    }
                ]
            },
            {
                "date": "08/11/2016",
                "sets": [
                    {
                        "weight": 20,
                        "reps": 8,
                        "split": "00:00:41:105",
                        "target": true
                    },
                    {
                        "weight": 20,
                        "reps": 8,
                        "split": "00:00:41:033",
                        "target": true
                    },
                    {
                        "weight": 20,
                        "reps": 8,
                        "split": "00:01:09:455",
                        "target": true
                    }
                ]
            },
            {
                "date": "15/11/2016",
                "sets": [
                    {
                        "weight": 20,
                        "reps": 8,
                        "split": "00:00:54:514",
                        "target": true
                    },
                    {
                        "weight": 20,
                        "reps": 8,
                        "split": "00:00:40:762",
                        "target": true
                    },
                    {
                        "weight": 20,
                        "reps": 8,
                        "split": "00:00:41:702",
                        "target": true
                    }
                ]
            }
        ]
    },
    {
        "exercise": "Wide lateral Raises",
        "sets": 3,
        "increase": 2.5,
        "peak": 3,
        "startPercent": 1,
        "endPercent": 1,
        "incInterval": 4,
        "equipmentWeight": 10,
        "sessions": [
            {
                "date": "14/10/2016",
                "sets": [
                    {
                        "weight": 20,
                        "reps": 8,
                        "split": "00:00:43:850",
                        "target": true
                    },
                    {
                        "weight": 20,
                        "reps": 8,
                        "split": "00:00:34:486",
                        "target": true
                    },
                    {
                        "weight": 20,
                        "reps": 8,
                        "split": "00:00:56:143",
                        "target": true
                    }
                ]
            },
            {
                "date": "22/10/2016",
                "sets": [
                    {
                        "weight": 20,
                        "reps": 8,
                        "split": "00:00:34:782",
                        "target": true
                    },
                    {
                        "weight": 20,
                        "reps": 8,
                        "split": "00:00:33:959",
                        "target": true
                    },
                    {
                        "weight": 20,
                        "reps": 8,
                        "split": "00:00:00:744",
                        "target": true
                    }
                ]
            },
            {
                "date": "31/10/2016",
                "sets": [
                    {
                        "weight": 20,
                        "reps": 8,
                        "split": "00:00:01:080",
                        "target": true
                    },
                    {
                        "weight": 20,
                        "reps": 8,
                        "split": "00:00:38:838",
                        "target": true
                    },
                    {
                        "weight": 20,
                        "reps": 8,
                        "split": "00:00:00:972",
                        "target": true
                    }
                ]
            },
            {
                "date": "08/11/2016",
                "sets": [
                    {
                        "weight": 20,
                        "reps": 8,
                        "split": "00:00:56:655",
                        "target": true
                    },
                    {
                        "weight": 20,
                        "reps": 8,
                        "split": "00:02:48:605",
                        "target": true
                    },
                    {
                        "weight": 20,
                        "reps": 8,
                        "split": "00:02:44:233",
                        "target": true
                    }
                ]
            },
            {
                "date": "15/11/2016",
                "sets": [
                    {
                        "weight": 20,
                        "reps": 8,
                        "split": "00:00:28:286",
                        "target": true
                    },
                    {
                        "weight": 20,
                        "reps": 8,
                        "split": "00:01:41:128",
                        "target": true
                    },
                    {
                        "weight": 20,
                        "reps": 8,
                        "split": "00:03:09:557",
                        "target": true
                    }
                ]
            }
        ]
    }
]